{
  "ETH": {
    "price": 1746.38,
    "score": 64,
    "time": 1782121966.0394182
  },
  "BTC": {
    "price": 64114.9,
    "score": 63,
    "time": 1782121966.0394182
  },
  "ZEREBRO": {
    "price": 0.04577,
    "score": 77,
    "time": 1781935272.6974788
  },
  "AAVE": {
    "price": 75.442,
    "score": 57,
    "time": 1782121966.0394182
  },
  "UB": {
    "price": 0.133139,
    "score": 55,
    "time": 1782121966.0394182
  },
  "HMSTR": {
    "price": 0.0001924,
    "score": 55,
    "time": 1782121966.0394182
  },
  "BNB": {
    "price": 592.64,
    "score": 56,
    "time": 1782121966.0394182
  },
  "LINK": {
    "price": 7.9852,
    "score": 56,
    "time": 1782121966.0394182
  },
  "SOL": {
    "price": 73.79,
    "score": 56,
    "time": 1782121740.1102586
  },
  "SUI": {
    "price": 0.7101,
    "score": 56,
    "time": 1782120324.1688974
  },
  "BILL": {
    "price": 0.06283,
    "score": 55,
    "time": 1782121966.0394182
  }
}