{
  "ETH": {
    "price": 1766.64,
    "score": 68,
    "time": 1782130333.5242786
  },
  "BTC": {
    "price": 64752.9,
    "score": 65,
    "time": 1782130333.5242786
  },
  "ZEREBRO": {
    "price": 0.04577,
    "score": 77,
    "time": 1781935272.6974788
  },
  "AAVE": {
    "price": 76.697,
    "score": 63,
    "time": 1782130333.5242786
  },
  "UB": {
    "price": 0.110818,
    "score": 55,
    "time": 1782130333.5242786
  },
  "HMSTR": {
    "price": 0.0001861,
    "score": 55,
    "time": 1782127822.3950548
  },
  "BNB": {
    "price": 597.344,
    "score": 59,
    "time": 1782130333.5242786
  },
  "LINK": {
    "price": 8.0974,
    "score": 60,
    "time": 1782130333.5242786
  },
  "SOL": {
    "price": 74.16,
    "score": 59,
    "time": 1782130333.5242786
  },
  "SUI": {
    "price": 0.7425,
    "score": 66,
    "time": 1782130333.5242786
  },
  "BILL": {
    "price": 0.0614,
    "score": 55,
    "time": 1782127859.1638997
  },
  "SYN": {
    "price": 0.283,
    "score": 55,
    "time": 1782130333.5242786
  },
  "W": {
    "price": 0.01311,
    "score": 55,
    "time": 1782127977.6080046
  },
  "TAO": {
    "price": 234.2,
    "score": 56,
    "time": 1782130333.5242786
  },
  "AVAX": {
    "price": 6.364,
    "score": 58,
    "time": 1782130333.5242786
  },
  "ADA": {
    "price": 0.1619,
    "score": 57,
    "time": 1782130333.5242786
  },
  "NEAR": {
    "price": 2.165,
    "score": 50,
    "time": 1782129812.4019842
  }
}