{
  "ETH": {
    "price": 1749.34,
    "score": 64,
    "time": 1782125426.9770832
  },
  "BTC": {
    "price": 64166.3,
    "score": 62,
    "time": 1782125426.9770832
  },
  "ZEREBRO": {
    "price": 0.04577,
    "score": 77,
    "time": 1781935272.6974788
  },
  "AAVE": {
    "price": 75.774,
    "score": 58,
    "time": 1782125426.9770832
  },
  "UB": {
    "price": 0.121067,
    "score": 55,
    "time": 1782125426.9770832
  },
  "HMSTR": {
    "price": 0.0001884,
    "score": 55,
    "time": 1782125426.9770832
  },
  "BNB": {
    "price": 591.951,
    "score": 56,
    "time": 1782125426.9770832
  },
  "LINK": {
    "price": 8.0011,
    "score": 56,
    "time": 1782125426.9770832
  },
  "SOL": {
    "price": 73.9,
    "score": 56,
    "time": 1782123508.4348102
  },
  "SUI": {
    "price": 0.7101,
    "score": 56,
    "time": 1782120324.1688974
  },
  "BILL": {
    "price": 0.0613,
    "score": 55,
    "time": 1782125426.9770832
  },
  "SYN": {
    "price": 0.2665,
    "score": 55,
    "time": 1782125426.9770832
  },
  "W": {
    "price": 0.01253,
    "score": 55,
    "time": 1782125183.4205987
  }
}