{
  "ETH": {
    "price": 1626.55,
    "score": 69,
    "time": 1782974726.8695073
  },
  "BTC": {
    "price": 60537.9,
    "score": 69,
    "time": 1782974726.8695073
  },
  "ZEREBRO": {
    "price": 0.04577,
    "score": 77,
    "time": 1781935272.6974788
  },
  "AAVE": {
    "price": 84.231,
    "score": 56,
    "time": 1782954822.9565797
  },
  "UB": {
    "price": 0.121691,
    "score": 55,
    "time": 1782830775.8798041
  },
  "HMSTR": {
    "price": 0.0001786,
    "score": 55,
    "time": 1782517358.7434697
  },
  "BNB": {
    "price": 550.76,
    "score": 57,
    "time": 1782974726.8695073
  },
  "LINK": {
    "price": 7.4802,
    "score": 63,
    "time": 1782974726.8695073
  },
  "SOL": {
    "price": 78.13,
    "score": 68,
    "time": 1782974726.8695073
  },
  "SUI": {
    "price": 0.7286,
    "score": 65,
    "time": 1782974726.8695073
  },
  "BILL": {
    "price": 0.04746,
    "score": 55,
    "time": 1782792194.4849274
  },
  "SYN": {
    "price": 0.5735,
    "score": 55,
    "time": 1782881574.8363478
  },
  "W": {
    "price": 0.0122,
    "score": 55,
    "time": 1782151936.574275
  },
  "TAO": {
    "price": 204.78,
    "score": 61,
    "time": 1782974726.8695073
  },
  "AVAX": {
    "price": 6.697,
    "score": 57,
    "time": 1782974726.8695073
  },
  "ADA": {
    "price": 0.1557,
    "score": 64,
    "time": 1782974726.8695073
  },
  "NEAR": {
    "price": 1.9189,
    "score": 68,
    "time": 1782974726.8695073
  },
  "ARX": {
    "price": 0.28948,
    "score": 55,
    "time": 1782788537.17977
  },
  "EIGEN": {
    "price": 0.308,
    "score": 55,
    "time": 1782140261.0148017
  },
  "LAB": {
    "price": 17.3772,
    "score": 55,
    "time": 1782661173.574369
  },
  "RE": {
    "price": 0.74119,
    "score": 55,
    "time": 1782813925.4769146
  },
  "TEL": {
    "price": 0.002752,
    "score": 55,
    "time": 1782166916.7920315
  },
  "RAIN": {
    "price": 0.016051,
    "score": 55,
    "time": 1782162660.7602031
  },
  "ILY": {
    "price": 0.1715,
    "score": 55,
    "time": 1782940317.05923
  },
  "DEXE": {
    "price": 23.259,
    "score": 55,
    "time": 1782259636.97038
  },
  "UMXM": {
    "price": 1.9386,
    "score": 55,
    "time": 1782212415.6876724
  },
  "FOLKS": {
    "price": 2.6121,
    "score": 55,
    "time": 1782236125.3602319
  },
  "ESPORTS": {
    "price": 0.0742,
    "score": 55,
    "time": 1782551989.4095166
  },
  "BEAT": {
    "price": 2.746,
    "score": 55,
    "time": 1782755937.3832269
  },
  "POPCAT": {
    "price": 0.05209,
    "score": 55,
    "time": 1782266240.9342792
  },
  "XPR": {
    "price": 0.0024748,
    "score": 55,
    "time": 1782273962.9065118
  },
  "BASED": {
    "price": 0.13368,
    "score": 55,
    "time": 1782972895.9732459
  },
  "GRASS": {
    "price": 0.521,
    "score": 55,
    "time": 1782572820.817536
  },
  "O": {
    "price": 0.60619,
    "score": 55,
    "time": 1782943952.5569696
  },
  "NES": {
    "price": 0.2006,
    "score": 55,
    "time": 1782965412.1479368
  },
  "VERONA": {
    "price": 0.1559,
    "score": 55,
    "time": 1782373774.8436847
  },
  "BAS": {
    "price": 0.04829,
    "score": 55,
    "time": 1782927649.5591023
  },
  "BLEND": {
    "price": 0.06036,
    "score": 55,
    "time": 1782431820.3253012
  },
  "SEI": {
    "price": 0.05764,
    "score": 55,
    "time": 1782410549.2452757
  },
  "INJ": {
    "price": 4.582,
    "score": 56,
    "time": 1782947568.0557353
  },
  "XPL": {
    "price": 0.1075,
    "score": 55,
    "time": 1782493685.4462054
  },
  "VVV": {
    "price": 13.685,
    "score": 55,
    "time": 1782482739.1440241
  },
  "IP": {
    "price": 0.36725,
    "score": 55,
    "time": 1782450431.1957524
  },
  "H": {
    "price": 0.083182,
    "score": 55,
    "time": 1782883405.7166538
  },
  "DN": {
    "price": 0.31797,
    "score": 55,
    "time": 1782940317.05923
  },
  "CAP": {
    "price": 0.029918,
    "score": 55,
    "time": 1782851570.6543515
  },
  "FARTCOIN": {
    "price": 0.146,
    "score": 55,
    "time": 1782735646.6459584
  },
  "VELVET": {
    "price": 1.75857,
    "score": 55,
    "time": 1782719083.357533
  },
  "ICNT": {
    "price": 0.24258,
    "score": 55,
    "time": 1782542929.048455
  },
  "KONET": {
    "price": 0.03151,
    "score": 55,
    "time": 1782510077.0556867
  },
  "RAVE": {
    "price": 0.428,
    "score": 55,
    "time": 1782783095.6821496
  },
  "PUMP": {
    "price": 0.001503,
    "score": 55,
    "time": 1782653861.3834908
  },
  "WIF": {
    "price": 0.1725,
    "score": 55,
    "time": 1782585435.6633039
  },
  "SIREN": {
    "price": 0.12357,
    "score": 55,
    "time": 1782563253.469849
  },
  "PIEVERSE": {
    "price": 0.7708,
    "score": 55,
    "time": 1782626492.484573
  },
  "S": {
    "price": 0.02632,
    "score": 55,
    "time": 1782671455.3635085
  },
  "GWEI": {
    "price": 0.180951,
    "score": 55,
    "time": 1782749883.940416
  },
  "BDX": {
    "price": 0.09614,
    "score": 55,
    "time": 1782659344.6757588
  },
  "MANTA": {
    "price": 0.0958,
    "score": 55,
    "time": 1782679497.0331764
  },
  "AI": {
    "price": 0.03411,
    "score": 55,
    "time": 1782873324.9421728
  },
  "ORDI": {
    "price": 3.848,
    "score": 55,
    "time": 1782810306.1760056
  },
  "STAY": {
    "price": 1.981e-05,
    "score": 55,
    "time": 1782821147.8738635
  },
  "ADI": {
    "price": 5.6747,
    "score": 55,
    "time": 1782806691.1772912
  },
  "IN": {
    "price": 0.21824,
    "score": 55,
    "time": 1782846158.8438025
  },
  "LIT": {
    "price": 2.108,
    "score": 55,
    "time": 1782974726.8695073
  },
  "XLM": {
    "price": 0.2032,
    "score": 55,
    "time": 1782918584.1897566
  },
  "DYDX": {
    "price": 0.1896,
    "score": 55,
    "time": 1782918584.1897566
  },
  "JUP": {
    "price": 0.2371,
    "score": 55,
    "time": 1782958455.1638303
  },
  "TAIKO": {
    "price": 0.3813,
    "score": 55,
    "time": 1782974726.8695073
  },
  "BIRB": {
    "price": 0.09925,
    "score": 55,
    "time": 1782974726.8695073
  }
}